{
  "accUserMode" : 2,
  "caption" : "计数器数据2",
  "codeName" : "CounterData2EditView",
  "dynaModelFilePath" : "PSSYSAPPS/Sample/PSAPPDEVIEWS/CounterData2EditView.json",
  "funcViewMode" : "EDITVIEW",
  "mOSFilePath" : "pssysapps/Sample/psappdeviews/CounterData2EditView",
  "name" : "CounterData2EditView",
  "openMode" : "DRAWER_RIGHT",
  "getPSAppDataEntity" : {
    "modelref" : true,
    "path" : "PSSYSAPPS/Sample/PSAPPDATAENTITIES/CounterData2.json"
  },
  "getPSAppModule" : {
    "modelref" : true,
    "path" : "PSSYSAPPS/Sample/PSAPPMODULES/Sample.json"
  },
  "getPSAppViewEngines" : [ {
    "engineCat" : "VIEW",
    "engineType" : "EditView",
    "mOSFilePath" : "psappviewengines/engine",
    "name" : "engine",
    "getPSUIEngineParams" : [ {
      "ctrlName" : "form",
      "name" : "FORM",
      "paramType" : "CTRL"
    }, {
      "name" : "P2K",
      "paramType" : "VALUE",
      "value" : 0
    } ],
    "rTMOSFilePath" : "psappviewengines/engine"
  } ],
  "getPSAppViewLogics" : [ {
    "eventArg" : "tbitem1",
    "eventNames" : "CLICK",
    "logicTrigger" : "CTRLEVENT",
    "logicType" : "APPVIEWUIACTION",
    "name" : "toolbar_tbitem1_click",
    "getPSAppViewUIAction" : {
      "modelref" : true,
      "id" : "toolbar_tbitem1"
    },
    "getPSViewCtrlName" : "toolbar"
  }, {
    "eventArg" : "tbitem2",
    "eventNames" : "CLICK",
    "logicTrigger" : "CTRLEVENT",
    "logicType" : "APPVIEWUIACTION",
    "name" : "toolbar_tbitem2_click",
    "getPSAppViewUIAction" : {
      "modelref" : true,
      "id" : "toolbar_tbitem2"
    },
    "getPSViewCtrlName" : "toolbar"
  } ],
  "getPSAppViewUIActions" : [ {
    "name" : "toolbar_tbitem1",
    "getPSUIAction" : {
      "modelref" : true,
      "id" : "SaveAndExit"
    },
    "xDataControlName" : "form"
  }, {
    "name" : "toolbar_tbitem2",
    "getPSUIAction" : {
      "modelref" : true,
      "id" : "Exit"
    },
    "xDataControlName" : "form"
  } ],
  "getPSControls" : [ {
    "codeName" : "EditViewtoolbar",
    "controlType" : "TOOLBAR",
    "hookEventNames" : [ "CLICK" ],
    "logicName" : "工具栏模板（弹出简单编辑表单，保存及关闭按钮）",
    "mOSFilePath" : "psmodules/Sample/psdataentities/COUNTERDATA2/psdetoolbars/EditViewtoolbar",
    "name" : "toolbar",
    "getPSAppDataEntity" : {
      "modelref" : true,
      "path" : "PSSYSAPPS/Sample/PSAPPDATAENTITIES/CounterData2.json"
    },
    "getPSControlLogics" : [ {
      "eventArg" : "tbitem1",
      "eventNames" : "CLICK",
      "logicTag" : "toolbar",
      "logicType" : "APPVIEWLOGIC",
      "name" : "toolbar_tbitem1_click",
      "getPSAppViewLogic" : {
        "modelref" : true,
        "id" : "toolbar_tbitem1_click"
      }
    }, {
      "eventArg" : "tbitem2",
      "eventNames" : "CLICK",
      "logicTag" : "toolbar",
      "logicType" : "APPVIEWLOGIC",
      "name" : "toolbar_tbitem2_click",
      "getPSAppViewLogic" : {
        "modelref" : true,
        "id" : "toolbar_tbitem2_click"
      }
    } ],
    "getPSControlParam" : {
      "id" : "TOOLBAR"
    },
    "getPSDEToolbarItems" : [ {
      "getCapPSLanguageRes" : {
        "lanResTag" : "TBB.TEXT.EDITVIEW.SAVEANDCLOSE",
        "mOSFilePath" : "pslanguageres/Auto97",
        "rTMOSFilePath" : "pslanguageres/Auto97"
      },
      "caption" : "保存并关闭",
      "groupExtractMode" : "ITEM",
      "itemType" : "DEUIACTION",
      "name" : "tbitem1",
      "noPrivDisplayMode" : 2,
      "getPSAppViewUIAction" : {
        "modelref" : true,
        "id" : "toolbar_tbitem1"
      },
      "getPSSysImage" : {
        "cssClass" : "sx-tb-saveandclose"
      },
      "getPSUIAction" : {
        "getCapPSLanguageRes" : {
          "lanResTag" : "TBB.TEXT.EDITVIEW.SAVEANDCLOSE",
          "mOSFilePath" : "pslanguageres/Auto97",
          "rTMOSFilePath" : "pslanguageres/Auto97"
        },
        "caption" : "保存并关闭",
        "codeName" : "SaveAndExit",
        "fullCodeName" : "SaveAndExit",
        "mOSFilePath" : "pssysappdeuiactions/SaveAndExit",
        "name" : "编辑界面_保存并退出操作",
        "getPSSysImage" : {
          "cssClass" : "sx-tb-saveandclose"
        },
        "rTMOSFilePath" : "pssysappdeuiactions/SaveAndExit",
        "timeout" : 60000,
        "getTooltipPSLanguageRes" : {
          "lanResTag" : "TBB.TOOLTIP.EDITVIEW.SAVEANDCLOSE",
          "mOSFilePath" : "pslanguageres/Auto43",
          "rTMOSFilePath" : "pslanguageres/Auto43"
        },
        "uIActionMode" : "SYS",
        "uIActionTag" : "SaveAndExit",
        "uIActionType" : "DEUIACTION"
      },
      "tooltip" : "保存并关闭",
      "getTooltipPSLanguageRes" : {
        "lanResTag" : "TBB.TOOLTIP.EDITVIEW.SAVEANDCLOSE",
        "mOSFilePath" : "pslanguageres/Auto43",
        "rTMOSFilePath" : "pslanguageres/Auto43"
      },
      "showCaption" : true,
      "showIcon" : true
    }, {
      "getCapPSLanguageRes" : {
        "lanResTag" : "TBB.TEXT.EDITVIEW.CLOSE",
        "mOSFilePath" : "pslanguageres/Auto223",
        "rTMOSFilePath" : "pslanguageres/Auto223"
      },
      "caption" : "关闭",
      "groupExtractMode" : "ITEM",
      "itemType" : "DEUIACTION",
      "name" : "tbitem2",
      "noPrivDisplayMode" : 2,
      "getPSAppViewUIAction" : {
        "modelref" : true,
        "id" : "toolbar_tbitem2"
      },
      "getPSSysImage" : {
        "glyph" : "xf08b@FontAwesome",
        "cssClass" : "fa fa-sign-out"
      },
      "getPSUIAction" : {
        "getCapPSLanguageRes" : {
          "lanResTag" : "TBB.TEXT.EDITVIEW.CLOSE",
          "mOSFilePath" : "pslanguageres/Auto223",
          "rTMOSFilePath" : "pslanguageres/Auto223"
        },
        "caption" : "关闭",
        "codeName" : "Exit",
        "fullCodeName" : "Exit",
        "mOSFilePath" : "pssysappdeuiactions/Exit",
        "name" : "编辑界面_退出操作",
        "getPSSysImage" : {
          "glyph" : "xf08b@FontAwesome",
          "cssClass" : "fa fa-sign-out"
        },
        "rTMOSFilePath" : "pssysappdeuiactions/Exit",
        "timeout" : 60000,
        "getTooltipPSLanguageRes" : {
          "lanResTag" : "TBB.TOOLTIP.EDITVIEW.CLOSE",
          "mOSFilePath" : "pslanguageres/Auto92",
          "rTMOSFilePath" : "pslanguageres/Auto92"
        },
        "uIActionMode" : "SYS",
        "uIActionTag" : "Exit",
        "uIActionType" : "DEUIACTION"
      },
      "tooltip" : "关闭",
      "getTooltipPSLanguageRes" : {
        "lanResTag" : "TBB.TOOLTIP.EDITVIEW.CLOSE",
        "mOSFilePath" : "pslanguageres/Auto92",
        "rTMOSFilePath" : "pslanguageres/Auto92"
      },
      "showCaption" : true,
      "showIcon" : true
    } ],
    "rTMOSFilePath" : "pssysapps/Sample/psappdeviews/CounterData2EditView/psappviewctrls/toolbar",
    "modelid" : "a6c665af2c16f3092af6051f2fa70a83",
    "modeltype" : "PSDETOOLBAR"
  }, {
    "codeName" : "Main",
    "controlType" : "FORM",
    "getCreatePSControlAction" : {
      "modelref" : true,
      "id" : "create"
    },
    "defaultLabelWidth" : 130,
    "dynaModelFilePath" : "PSSYSAPPS/Sample/PSAPPDATAENTITIES/CounterData2/PSFORMS/Main.json",
    "getGetDraftFromPSControlAction" : {
      "modelref" : true,
      "id" : "loaddraftfrom"
    },
    "getGetDraftPSControlAction" : {
      "modelref" : true,
      "id" : "loaddraft"
    },
    "getGetPSControlAction" : {
      "modelref" : true,
      "id" : "load"
    },
    "hookEventNames" : [ "SAVE", "REMOVE", "LOAD" ],
    "logicName" : "主编辑表单",
    "mOSFilePath" : "psmodules/Sample/psdataentities/COUNTERDATA2/psdeform_editforms/Main",
    "getPSAppDataEntity" : {
      "modelref" : true,
      "path" : "PSSYSAPPS/Sample/PSAPPDATAENTITIES/CounterData2.json"
    },
    "getPSControlHandler" : {
      "getPSHandlerActions" : [ {
        "actionName" : "Update",
        "actionType" : "DEACTION",
        "dataAccessAction" : "UPDATE",
        "name" : "update",
        "getPSAppDEMethod" : {
          "modelref" : true,
          "id" : "Update"
        },
        "getPSAppDataEntity" : {
          "modelref" : true,
          "path" : "PSSYSAPPS/Sample/PSAPPDATAENTITIES/CounterData2.json"
        }
      }, {
        "actionName" : "GETDRAFTFROM",
        "actionType" : "DEACTION",
        "dataAccessAction" : "CREATE",
        "name" : "loaddraftfrom",
        "getPSAppDataEntity" : {
          "modelref" : true,
          "path" : "PSSYSAPPS/Sample/PSAPPDATAENTITIES/CounterData2.json"
        }
      }, {
        "actionName" : "Remove",
        "actionType" : "DEACTION",
        "dataAccessAction" : "DELETE",
        "name" : "remove",
        "getPSAppDEMethod" : {
          "modelref" : true,
          "id" : "Remove"
        },
        "getPSAppDataEntity" : {
          "modelref" : true,
          "path" : "PSSYSAPPS/Sample/PSAPPDATAENTITIES/CounterData2.json"
        }
      }, {
        "actionName" : "GetDraft",
        "actionType" : "DEACTION",
        "dataAccessAction" : "CREATE",
        "name" : "loaddraft",
        "getPSAppDEMethod" : {
          "modelref" : true,
          "id" : "GetDraft"
        },
        "getPSAppDataEntity" : {
          "modelref" : true,
          "path" : "PSSYSAPPS/Sample/PSAPPDATAENTITIES/CounterData2.json"
        }
      }, {
        "actionName" : "Get",
        "actionType" : "DEACTION",
        "dataAccessAction" : "READ",
        "name" : "load",
        "getPSAppDEMethod" : {
          "modelref" : true,
          "id" : "Get"
        },
        "getPSAppDataEntity" : {
          "modelref" : true,
          "path" : "PSSYSAPPS/Sample/PSAPPDATAENTITIES/CounterData2.json"
        }
      }, {
        "actionName" : "Create",
        "actionType" : "DEACTION",
        "dataAccessAction" : "CREATE",
        "name" : "create",
        "getPSAppDEMethod" : {
          "modelref" : true,
          "id" : "Create"
        },
        "getPSAppDataEntity" : {
          "modelref" : true,
          "path" : "PSSYSAPPS/Sample/PSAPPDATAENTITIES/CounterData2.json"
        }
      } ],
      "enableDEFieldPrivilege" : false,
      "id" : "编辑表单处理器"
    },
    "getPSControlLogics" : [ {
      "eventNames" : "LOAD;SAVE;REMOVE",
      "logicTag" : "form",
      "logicType" : "APPVIEWENGINE",
      "name" : "engine_form",
      "getPSAppViewEngine" : {
        "modelref" : true,
        "id" : "engine"
      }
    } ],
    "getPSControlParam" : {
      "autoLoad" : true,
      "showBusyIndicator" : true,
      "id" : "FORM"
    },
    "getPSDEFormItems" : [ {
      "id" : "srfupdatedate",
      "hidden" : true,
      "dataType" : 5,
      "getPSAppDEField" : {
        "name" : "UPDATEDATE",
        "codeName" : "UpdateDate"
      }
    }, {
      "id" : "srforikey",
      "hidden" : true,
      "dataType" : 25
    }, {
      "id" : "srfkey",
      "hidden" : true,
      "dataType" : 25,
      "getPSAppDEField" : {
        "name" : "COUNTERDATA2ID",
        "codeName" : "CounterData2Id"
      }
    }, {
      "id" : "srfmajortext",
      "hidden" : true,
      "dataType" : 25,
      "getPSAppDEField" : {
        "name" : "COUNTERDATA2NAME",
        "codeName" : "CounterData2Name"
      }
    }, {
      "id" : "srftempmode",
      "hidden" : true,
      "dataType" : 25
    }, {
      "id" : "srfuf",
      "hidden" : true,
      "dataType" : 25
    }, {
      "id" : "srfdeid",
      "hidden" : true,
      "dataType" : 25
    }, {
      "id" : "srfsourcekey",
      "hidden" : true,
      "dataType" : 25
    }, {
      "id" : "countertag",
      "dataType" : 9,
      "getPSAppDEField" : {
        "name" : "COUNTERTAG",
        "codeName" : "Countertag"
      }
    }, {
      "id" : "countertag2",
      "dataType" : 9,
      "getPSAppDEField" : {
        "name" : "COUNTERTAG2",
        "codeName" : "Countertag2"
      }
    }, {
      "id" : "countertag3",
      "dataType" : 9,
      "getPSAppDEField" : {
        "name" : "COUNTERTAG3",
        "codeName" : "Countertag3"
      }
    }, {
      "id" : "countertag4",
      "dataType" : 9,
      "getPSAppDEField" : {
        "name" : "COUNTERTAG4",
        "codeName" : "Countertag4"
      }
    }, {
      "id" : "countertag5",
      "dataType" : 9,
      "getPSAppDEField" : {
        "name" : "COUNTERTAG5",
        "codeName" : "Countertag5"
      }
    }, {
      "id" : "countertag6",
      "dataType" : 9,
      "getPSAppDEField" : {
        "name" : "COUNTERTAG6",
        "codeName" : "Countertag6"
      }
    }, {
      "id" : "countertag7",
      "dataType" : 9,
      "getPSAppDEField" : {
        "name" : "COUNTERTAG7",
        "codeName" : "Countertag7"
      }
    }, {
      "id" : "countertag8",
      "dataType" : 9,
      "getPSAppDEField" : {
        "name" : "COUNTERTAG8",
        "codeName" : "Countertag8"
      }
    }, {
      "id" : "countertag9",
      "dataType" : 9,
      "getPSAppDEField" : {
        "name" : "COUNTERTAG9",
        "codeName" : "Countertag9"
      }
    }, {
      "id" : "counterdata2id",
      "hidden" : true,
      "dataType" : 25,
      "getPSAppDEField" : {
        "name" : "COUNTERDATA2ID",
        "codeName" : "CounterData2Id"
      }
    } ],
    "getPSDEFormPages" : [ {
      "caption" : "基本信息",
      "codeName" : "formpage1",
      "detailStyle" : "DEFAULT",
      "detailType" : "FORMPAGE",
      "mOSFilePath" : "psdeformdetail_formpages/formpage1",
      "name" : "formpage1",
      "getPSDEFormDetails" : [ {
        "actionGroupExtractMode" : "ITEM",
        "caption" : "计算器数据2基本信息",
        "codeName" : "group1",
        "detailStyle" : "DEFAULT",
        "detailType" : "GROUPPANEL",
        "mOSFilePath" : "psdeformdetail_grouppanels/group1",
        "name" : "group1",
        "getPSDEFormDetails" : [ {
          "caption" : "计数1",
          "codeName" : "countertag",
          "dataType" : 9,
          "detailStyle" : "DEFAULT",
          "detailType" : "FORMITEM",
          "enableCond" : 3,
          "ignoreInput" : 0,
          "labelPos" : "LEFT",
          "labelWidth" : 130,
          "mOSFilePath" : "psdeformdetail_formitems/countertag",
          "name" : "countertag",
          "noPrivDisplayMode" : 1,
          "getPSAppDEField" : {
            "name" : "COUNTERTAG",
            "codeName" : "Countertag"
          },
          "getPSEditor" : {
            "editorType" : "TEXTBOX",
            "name" : "countertag"
          },
          "getPSLayoutPos" : {
            "colLG" : 8,
            "colMD" : 24,
            "layout" : "TABLE_24COL"
          },
          "rTMOSFilePath" : "psdeformdetail_formitems/countertag",
          "allowEmpty" : true,
          "showCaption" : true
        }, {
          "caption" : "计数2",
          "codeName" : "countertag2",
          "dataType" : 9,
          "detailStyle" : "DEFAULT",
          "detailType" : "FORMITEM",
          "enableCond" : 3,
          "ignoreInput" : 0,
          "labelPos" : "LEFT",
          "labelWidth" : 130,
          "mOSFilePath" : "psdeformdetail_formitems/countertag2",
          "name" : "countertag2",
          "noPrivDisplayMode" : 1,
          "getPSAppDEField" : {
            "name" : "COUNTERTAG2",
            "codeName" : "Countertag2"
          },
          "getPSEditor" : {
            "editorType" : "TEXTBOX",
            "name" : "countertag2"
          },
          "getPSLayoutPos" : {
            "colLG" : 8,
            "colMD" : 24,
            "layout" : "TABLE_24COL"
          },
          "rTMOSFilePath" : "psdeformdetail_formitems/countertag2",
          "allowEmpty" : true,
          "showCaption" : true
        }, {
          "caption" : "计数3",
          "codeName" : "countertag3",
          "dataType" : 9,
          "detailStyle" : "DEFAULT",
          "detailType" : "FORMITEM",
          "enableCond" : 3,
          "ignoreInput" : 0,
          "labelPos" : "LEFT",
          "labelWidth" : 130,
          "mOSFilePath" : "psdeformdetail_formitems/countertag3",
          "name" : "countertag3",
          "noPrivDisplayMode" : 1,
          "getPSAppDEField" : {
            "name" : "COUNTERTAG3",
            "codeName" : "Countertag3"
          },
          "getPSEditor" : {
            "editorType" : "TEXTBOX",
            "name" : "countertag3"
          },
          "getPSLayoutPos" : {
            "colLG" : 8,
            "colMD" : 24,
            "layout" : "TABLE_24COL"
          },
          "rTMOSFilePath" : "psdeformdetail_formitems/countertag3",
          "allowEmpty" : true,
          "showCaption" : true
        }, {
          "caption" : "计数4",
          "codeName" : "countertag4",
          "dataType" : 9,
          "detailStyle" : "DEFAULT",
          "detailType" : "FORMITEM",
          "enableCond" : 3,
          "ignoreInput" : 0,
          "labelPos" : "LEFT",
          "labelWidth" : 130,
          "mOSFilePath" : "psdeformdetail_formitems/countertag4",
          "name" : "countertag4",
          "noPrivDisplayMode" : 1,
          "getPSAppDEField" : {
            "name" : "COUNTERTAG4",
            "codeName" : "Countertag4"
          },
          "getPSEditor" : {
            "editorType" : "TEXTBOX",
            "name" : "countertag4"
          },
          "getPSLayoutPos" : {
            "colLG" : 8,
            "colMD" : 24,
            "layout" : "TABLE_24COL"
          },
          "rTMOSFilePath" : "psdeformdetail_formitems/countertag4",
          "allowEmpty" : true,
          "showCaption" : true
        }, {
          "caption" : "计数5",
          "codeName" : "countertag5",
          "dataType" : 9,
          "detailStyle" : "DEFAULT",
          "detailType" : "FORMITEM",
          "enableCond" : 3,
          "ignoreInput" : 0,
          "labelPos" : "LEFT",
          "labelWidth" : 130,
          "mOSFilePath" : "psdeformdetail_formitems/countertag5",
          "name" : "countertag5",
          "noPrivDisplayMode" : 1,
          "getPSAppDEField" : {
            "name" : "COUNTERTAG5",
            "codeName" : "Countertag5"
          },
          "getPSEditor" : {
            "editorType" : "TEXTBOX",
            "name" : "countertag5"
          },
          "getPSLayoutPos" : {
            "colLG" : 8,
            "colMD" : 24,
            "layout" : "TABLE_24COL"
          },
          "rTMOSFilePath" : "psdeformdetail_formitems/countertag5",
          "allowEmpty" : true,
          "showCaption" : true
        }, {
          "caption" : "计数6",
          "codeName" : "countertag6",
          "dataType" : 9,
          "detailStyle" : "DEFAULT",
          "detailType" : "FORMITEM",
          "enableCond" : 3,
          "ignoreInput" : 0,
          "labelPos" : "LEFT",
          "labelWidth" : 130,
          "mOSFilePath" : "psdeformdetail_formitems/countertag6",
          "name" : "countertag6",
          "noPrivDisplayMode" : 1,
          "getPSAppDEField" : {
            "name" : "COUNTERTAG6",
            "codeName" : "Countertag6"
          },
          "getPSEditor" : {
            "editorType" : "TEXTBOX",
            "name" : "countertag6"
          },
          "getPSLayoutPos" : {
            "colLG" : 8,
            "colMD" : 24,
            "layout" : "TABLE_24COL"
          },
          "rTMOSFilePath" : "psdeformdetail_formitems/countertag6",
          "allowEmpty" : true,
          "showCaption" : true
        }, {
          "caption" : "计数7",
          "codeName" : "countertag7",
          "dataType" : 9,
          "detailStyle" : "DEFAULT",
          "detailType" : "FORMITEM",
          "enableCond" : 3,
          "ignoreInput" : 0,
          "labelPos" : "LEFT",
          "labelWidth" : 130,
          "mOSFilePath" : "psdeformdetail_formitems/countertag7",
          "name" : "countertag7",
          "noPrivDisplayMode" : 1,
          "getPSAppDEField" : {
            "name" : "COUNTERTAG7",
            "codeName" : "Countertag7"
          },
          "getPSEditor" : {
            "editorType" : "TEXTBOX",
            "name" : "countertag7"
          },
          "getPSLayoutPos" : {
            "colLG" : 8,
            "colMD" : 24,
            "layout" : "TABLE_24COL"
          },
          "rTMOSFilePath" : "psdeformdetail_formitems/countertag7",
          "allowEmpty" : true,
          "showCaption" : true
        }, {
          "caption" : "计数8",
          "codeName" : "countertag8",
          "dataType" : 9,
          "detailStyle" : "DEFAULT",
          "detailType" : "FORMITEM",
          "enableCond" : 3,
          "ignoreInput" : 0,
          "labelPos" : "LEFT",
          "labelWidth" : 130,
          "mOSFilePath" : "psdeformdetail_formitems/countertag8",
          "name" : "countertag8",
          "noPrivDisplayMode" : 1,
          "getPSAppDEField" : {
            "name" : "COUNTERTAG8",
            "codeName" : "Countertag8"
          },
          "getPSEditor" : {
            "editorType" : "TEXTBOX",
            "name" : "countertag8"
          },
          "getPSLayoutPos" : {
            "colLG" : 8,
            "colMD" : 24,
            "layout" : "TABLE_24COL"
          },
          "rTMOSFilePath" : "psdeformdetail_formitems/countertag8",
          "allowEmpty" : true,
          "showCaption" : true
        }, {
          "caption" : "计数9",
          "codeName" : "countertag9",
          "dataType" : 9,
          "detailStyle" : "DEFAULT",
          "detailType" : "FORMITEM",
          "enableCond" : 3,
          "ignoreInput" : 0,
          "labelPos" : "LEFT",
          "labelWidth" : 130,
          "mOSFilePath" : "psdeformdetail_formitems/countertag9",
          "name" : "countertag9",
          "noPrivDisplayMode" : 1,
          "getPSAppDEField" : {
            "name" : "COUNTERTAG9",
            "codeName" : "Countertag9"
          },
          "getPSEditor" : {
            "editorType" : "TEXTBOX",
            "name" : "countertag9"
          },
          "getPSLayoutPos" : {
            "colLG" : 8,
            "colMD" : 24,
            "layout" : "TABLE_24COL"
          },
          "rTMOSFilePath" : "psdeformdetail_formitems/countertag9",
          "allowEmpty" : true,
          "showCaption" : true
        } ],
        "getPSLayout" : {
          "childColLG" : 8,
          "childColMD" : 24,
          "childColSM" : -1,
          "childColXS" : -1,
          "columnCount" : 24,
          "layout" : "TABLE_24COL"
        },
        "getPSLayoutPos" : {
          "colMD" : 24,
          "layout" : "TABLE_24COL"
        },
        "rTMOSFilePath" : "psdeformdetail_grouppanels/group1",
        "infoGroupMode" : false,
        "showCaption" : false
      } ],
      "getPSLayout" : {
        "childColLG" : -1,
        "childColMD" : 24,
        "childColSM" : -1,
        "childColXS" : -1,
        "columnCount" : 24,
        "layout" : "TABLE_24COL"
      },
      "rTMOSFilePath" : "psdeformdetail_formpages/formpage1",
      "infoGroupMode" : false
    } ],
    "getPSLayout" : {
      "childColLG" : -1,
      "childColMD" : 24,
      "childColSM" : -1,
      "childColXS" : -1,
      "columnCount" : 24,
      "layout" : "TABLE_24COL"
    },
    "rTMOSFilePath" : "pssysapps/Sample/psappdeviews/CounterData2EditView/psappviewctrls/form",
    "getRemovePSControlAction" : {
      "modelref" : true,
      "id" : "remove"
    },
    "tabHeaderPos" : "TOP",
    "getUpdatePSControlAction" : {
      "modelref" : true,
      "id" : "update"
    },
    "noTabHeader" : true,
    "name" : "form",
    "modelid" : "373eecbf6dd0f7c0c65f592315c1a2d7",
    "modeltype" : "PSDEFORM_EDITFORM"
  } ],
  "getPSDEViewCodeName" : "EditView",
  "getPSDEViewId" : "f2c9077893846a0d54a4deb5829ac6e2",
  "getPSViewLayoutPanel" : {
    "codeName" : "Layoutpanel",
    "controlStyle" : "APPDEEDITVIEW",
    "controlType" : "VIEWLAYOUTPANEL",
    "mOSFilePath" : "psmodules/Sample/psdataentities/COUNTERDATA2/pssysviewlayoutpanels/Layoutpanel",
    "name" : "layoutpanel",
    "getPSAppDataEntity" : {
      "modelref" : true,
      "path" : "PSSYSAPPS/Sample/PSAPPDATAENTITIES/CounterData2.json"
    },
    "getPSControlParam" : { },
    "rTMOSFilePath" : "pssysapps/Sample/psappdeviews/CounterData2EditView/psappviewctrls/layoutpanel",
    "layoutBodyOnly" : true,
    "layoutPanel" : true,
    "useDefaultLayout" : true
  },
  "rTMOSFilePath" : "pssysapps/Sample/psappdeviews/CounterData2EditView",
  "title" : "计数器数据2编辑视图",
  "viewStyle" : "DEFAULT",
  "viewType" : "DEEDITVIEW",
  "width" : 700,
  "xDataControlName" : "form",
  "enableDP" : true,
  "showDataInfoBar" : true,
  "modelid" : "b49dfec4204c46fb209cb6f68b9a3614",
  "modeltype" : "PSAPPDEVIEW"
}